pynapl/HTeMaiL.py
pynapl/__init__.py
pynapl-0.0.8.dist-info/LICENSE
pynapl-0.0.8.dist-info/METADATA
pynapl-0.0.8.dist-info/WHEEL
pynapl-0.0.8.dist-info/top_level.txt
pynapl-0.0.8.dist-info/RECORD
