Metadata-Version: 2.1
Name: pynapl
Version: 0.0.8
Summary: Python Native Automation Package Library
Home-page: https://github.com/sgriffith3/pynapl
Author: Sam Griffith
Author-email: samgriffith3@gmail.com
License: UNKNOWN
Platform: UNKNOWN
Classifier: Programming Language :: Python :: 3
Classifier: License :: OSI Approved :: MIT License
Classifier: Operating System :: OS Independent
